LovU/__init__.py
LovU/getName.py
LovU/main.py
LovU/me.py
LovU/message.py
LovU-0.0.1.dist-info/LICENSE
LovU-0.0.1.dist-info/METADATA
LovU-0.0.1.dist-info/WHEEL
LovU-0.0.1.dist-info/top_level.txt
LovU-0.0.1.dist-info/RECORD
