Metadata-Version: 2.1
Name: LovU
Version: 0.0.1
Summary: Say Love in more than 100 languages~
Home-page: https://github.com/yaakovazat/LovU
Author: Yaakov Azat
Author-email: yaakovazat@gmail.com
License: UNKNOWN
Platform: UNKNOWN
Classifier: Programming Language :: Python :: 3
Classifier: License :: OSI Approved :: MIT License
Classifier: Operating System :: OS Independent
